odoo/addons/account_invoice_report_grouped_by_picking/README.rst
odoo/addons/account_invoice_report_grouped_by_picking/__init__.py
odoo/addons/account_invoice_report_grouped_by_picking/__manifest__.py
odoo/addons/account_invoice_report_grouped_by_picking/i18n/account_invoice_report_grouped_by_picking.pot
odoo/addons/account_invoice_report_grouped_by_picking/i18n/es.po
odoo/addons/account_invoice_report_grouped_by_picking/i18n/pt.po
odoo/addons/account_invoice_report_grouped_by_picking/i18n/sl.po
odoo/addons/account_invoice_report_grouped_by_picking/models/__init__.py
odoo/addons/account_invoice_report_grouped_by_picking/models/account_invoice.py
odoo/addons/account_invoice_report_grouped_by_picking/readme/CONTRIBUTORS.rst
odoo/addons/account_invoice_report_grouped_by_picking/readme/DESCRIPTION.rst
odoo/addons/account_invoice_report_grouped_by_picking/readme/ROADMAP.rst
odoo/addons/account_invoice_report_grouped_by_picking/readme/USAGE.rst
odoo/addons/account_invoice_report_grouped_by_picking/security/portal_security.xml
odoo/addons/account_invoice_report_grouped_by_picking/static/description/icon.png
odoo/addons/account_invoice_report_grouped_by_picking/static/description/index.html
odoo/addons/account_invoice_report_grouped_by_picking/tests/__init__.py
odoo/addons/account_invoice_report_grouped_by_picking/tests/test_account_invoice_group_picking.py
odoo/addons/account_invoice_report_grouped_by_picking/views/report_invoice.xml
odoo12_addon_account_invoice_report_grouped_by_picking-12.0.1.1.1.dist-info/METADATA
odoo12_addon_account_invoice_report_grouped_by_picking-12.0.1.1.1.dist-info/WHEEL
odoo12_addon_account_invoice_report_grouped_by_picking-12.0.1.1.1.dist-info/top_level.txt
odoo12_addon_account_invoice_report_grouped_by_picking-12.0.1.1.1.dist-info/RECORD
