Metadata-Version: 2.1
Name: odoo12-addon-account-invoice-report-grouped-by-picking
Version: 12.0.1.1.1
Summary: Print invoice lines grouped by picking
Home-page: https://github.com/OCA/account-invoice-reporting
Author: Tecnativa, Odoo Community Association (OCA)
Author-email: support@odoo-community.org
License: AGPL-3
Platform: UNKNOWN
Classifier: Programming Language :: Python
Classifier: Framework :: Odoo
Classifier: License :: OSI Approved :: GNU Affero General Public License v3
Requires-Python: >=3.5
Requires-Dist: odoo12-addon-stock-picking-invoice-link
Requires-Dist: odoo (<12.1dev,>=12.0a)
